{
	"format_version": "1.8.0",
	"animations": {
		"Ted_Walk": {
			"loop": true,
			"animation_length": 1.25,
			"bones": {
				"hed": {
					"rotation": {
						"0.0": {
							"vector": [-12.5, 0, 0]
						},
						"0.2917": {
							"vector": [-15, 0, 0]
						},
						"0.625": {
							"vector": [-12.5, 0, 0]
						},
						"0.9167": {
							"vector": [-15, 0, 0]
						},
						"1.25": {
							"vector": [-12.5, 0, 0]
						}
					}
				},
				"longpartlegleft": {
					"rotation": {
						"0.0": {
							"vector": [0, 0, 0]
						},
						"0.2917": {
							"vector": [-32.5, 0, 0]
						},
						"0.625": {
							"vector": [0, 0, 0]
						},
						"0.9167": {
							"vector": [22.5, 0, 0]
						},
						"1.25": {
							"vector": [0, 0, 0]
						}
					}
				},
				"longpart_left_leg_bottom": {
					"rotation": {
						"0.0": {
							"vector": [0.36, 0, 0]
						},
						"0.2917": {
							"vector": [22.5, 0, 0]
						},
						"0.625": {
							"vector": [0.36, 0, 0]
						},
						"0.9167": {
							"vector": [7.5, 0, 0]
						},
						"1.25": {
							"vector": [0.36, 0, 0]
						}
					}
				},
				"footleft": {
					"rotation": {
						"0.0": {
							"vector": [0.71, 0, 0]
						},
						"0.2917": {
							"vector": [10, 0, 0]
						},
						"0.625": {
							"vector": [0.71, 0, 0]
						},
						"0.9167": {
							"vector": [7.5, 0, 0]
						},
						"1.25": {
							"vector": [0.71, 0, 0]
						}
					}
				},
				"longpartrightleg": {
					"rotation": {
						"0.0": {
							"vector": [0, 0, 0]
						},
						"0.2917": {
							"vector": [12.5, 0, 0]
						},
						"0.625": {
							"vector": [0, 0, 0]
						},
						"0.9167": {
							"vector": [-37.5, 0, 0]
						},
						"1.25": {
							"vector": [0, 0, 0]
						}
					}
				},
				"longpart_right_leg_bottom": {
					"rotation": {
						"0.0": {
							"vector": [0, 0, 0]
						},
						"0.2917": {
							"vector": [7.5, 0, 0]
						},
						"0.625": {
							"vector": [0, 0, 0]
						},
						"0.9167": {
							"vector": [30, 0, 0]
						},
						"1.25": {
							"vector": [0, 0, 0]
						}
					}
				},
				"rightfoot": {
					"rotation": {
						"0.0": {
							"vector": [0, 0, 0]
						},
						"0.2917": {
							"vector": [12.5, 0, 0]
						},
						"0.625": {
							"vector": [0, 0, 0]
						},
						"0.9167": {
							"vector": [10, 0, 0]
						},
						"1.25": {
							"vector": [0, 0, 0]
						}
					}
				},
				"longpart_right_arm": {
					"rotation": {
						"0.0": {
							"vector": [29.97638, 1.2497, -87.16541]
						},
						"0.2917": {
							"vector": [32.47638, 1.2497, -87.16541]
						},
						"0.625": {
							"vector": [29.97638, 1.2497, -87.16541]
						},
						"0.9167": {
							"vector": [32.47638, 1.2497, -87.16541]
						},
						"1.25": {
							"vector": [29.97638, 1.2497, -87.16541]
						}
					},
					"position": {
						"0.0": {
							"vector": [-2, -1, 0]
						},
						"0.2917": {
							"vector": [-2, 0, 0]
						},
						"0.625": {
							"vector": [-2, -1, 0]
						},
						"0.9167": {
							"vector": [-2, 0, 0]
						},
						"1.25": {
							"vector": [-2, -1, 0]
						}
					}
				},
				"nails2": {
					"rotation": {
						"0.0": {
							"vector": [0, 0, 10]
						},
						"0.2917": {
							"vector": [0, 0, 15]
						},
						"0.625": {
							"vector": [0, 0, 10]
						},
						"0.9167": {
							"vector": [0, 0, 15]
						},
						"1.25": {
							"vector": [0, 0, 10]
						}
					}
				},
				"nail3": {
					"rotation": {
						"0.0": {
							"vector": [0, 0, 7.5]
						},
						"0.2917": {
							"vector": [0, 0, 12.5]
						},
						"0.625": {
							"vector": [0, 0, 7.5]
						},
						"0.9167": {
							"vector": [0, 0, 12.5]
						},
						"1.25": {
							"vector": [0, 0, 7.5]
						}
					}
				},
				"nails4": {
					"rotation": {
						"0.0": {
							"vector": [0, 0, 10]
						},
						"0.2917": {
							"vector": [0, 0, 15]
						},
						"0.625": {
							"vector": [0, 0, 10]
						},
						"0.9167": {
							"vector": [0, 0, 15]
						},
						"1.25": {
							"vector": [0, 0, 10]
						}
					}
				},
				"longpart_left_arm": {
					"rotation": {
						"0.0": {
							"vector": [60.02362, -88.7503, 92.16541]
						},
						"0.2917": {
							"vector": [57.52362, -88.7503, 92.16541]
						},
						"0.625": {
							"vector": [60.02362, -88.7503, 92.16541]
						},
						"0.9167": {
							"vector": [57.52362, -88.7503, 92.16541]
						},
						"1.25": {
							"vector": [60.02362, -88.7503, 92.16541]
						}
					},
					"position": {
						"0.0": {
							"vector": [2, 0, 1]
						},
						"0.2917": {
							"vector": [2, 0, 0]
						},
						"0.625": {
							"vector": [2, 0, 1]
						},
						"0.9167": {
							"vector": [2, 0, 0]
						},
						"1.25": {
							"vector": [2, 0, 1]
						}
					}
				},
				"nails1": {
					"rotation": {
						"0.0": {
							"vector": [0, 0, 10]
						},
						"0.2917": {
							"vector": [0, 0, 15]
						},
						"0.625": {
							"vector": [0, 0, 10]
						},
						"0.9167": {
							"vector": [0, 0, 15]
						},
						"1.25": {
							"vector": [0, 0, 10]
						}
					}
				},
				"nail2": {
					"rotation": {
						"0.0": {
							"vector": [0, 0, 10]
						},
						"0.2917": {
							"vector": [0, 0, 15]
						},
						"0.625": {
							"vector": [0, 0, 10]
						},
						"0.9167": {
							"vector": [0, 0, 15]
						},
						"1.25": {
							"vector": [0, 0, 10]
						}
					}
				},
				"nails3": {
					"rotation": {
						"0.0": {
							"vector": [0, 0, 10]
						},
						"0.2917": {
							"vector": [0, 0, 15]
						},
						"0.625": {
							"vector": [0, 0, 10]
						},
						"0.9167": {
							"vector": [0, 0, 15]
						},
						"1.25": {
							"vector": [0, 0, 10]
						}
					}
				},
				"bone11": {
					"rotation": {
						"0.0": {
							"vector": [5, 0, 0]
						},
						"0.2917": {
							"vector": [2.5, 0, 0]
						},
						"0.625": {
							"vector": [5, 0, 0]
						},
						"0.9167": {
							"vector": [2.5, 0, 0]
						},
						"1.25": {
							"vector": [5, 0, 0]
						}
					}
				},
				"bone12": {
					"rotation": {
						"0.0": {
							"vector": [17.5, 0, 0]
						},
						"0.2917": {
							"vector": [15, 0, 0]
						},
						"0.625": {
							"vector": [17.5, 0, 0]
						},
						"0.9167": {
							"vector": [15, 0, 0]
						},
						"1.25": {
							"vector": [17.5, 0, 0]
						}
					}
				},
				"bone13": {
					"rotation": {
						"vector": [5, 0, 0]
					}
				},
				"Ted": {
					"position": {
						"0.0": {
							"vector": [0, 0, 0]
						},
						"0.2917": {
							"vector": [0, 1, 0]
						},
						"0.625": {
							"vector": [0, 0, 0]
						},
						"0.9167": {
							"vector": [0, 1, 0]
						},
						"1.25": {
							"vector": [0, 0, 0]
						}
					}
				},
				"thumbnail1": {
					"rotation": {
						"0.0": {
							"vector": [0, 0, 0]
						},
						"0.2917": {
							"vector": [0, 0, 5]
						},
						"0.625": {
							"vector": [0, 0, 0]
						},
						"0.9167": {
							"vector": [0, 0, 5]
						},
						"1.25": {
							"vector": [0, 0, 0]
						}
					}
				},
				"thumbnail2": {
					"rotation": {
						"0.0": {
							"vector": [0, 0, 0]
						},
						"0.2917": {
							"vector": [0, 0, 5]
						},
						"0.625": {
							"vector": [0, 0, 0]
						},
						"0.9167": {
							"vector": [0, 0, 5]
						},
						"1.25": {
							"vector": [0, 0, 0]
						}
					}
				},
				"thumbnail4": {
					"rotation": {
						"0.0": {
							"vector": [0, 0, 0]
						},
						"0.2917": {
							"vector": [0, 0, 5]
						},
						"0.625": {
							"vector": [0, 0, 0]
						},
						"0.9167": {
							"vector": [0, 0, 5]
						},
						"1.25": {
							"vector": [0, 0, 0]
						}
					}
				},
				"thumbnail5": {
					"rotation": {
						"0.0": {
							"vector": [0, 0, 0]
						},
						"0.2917": {
							"vector": [0, 0, 5]
						},
						"0.625": {
							"vector": [0, 0, 0]
						},
						"0.9167": {
							"vector": [0, 0, 5]
						},
						"1.25": {
							"vector": [0, 0, 0]
						}
					}
				},
				"thumbnail6": {
					"rotation": {
						"0.0": {
							"vector": [0, 0, 0]
						},
						"0.2917": {
							"vector": [0, 0, 0]
						}
					}
				},
				"ears": {
					"rotation": {
						"0.0": {
							"vector": [0, 0, 0]
						},
						"0.2917": {
							"vector": [10, 0, 0]
						},
						"0.625": {
							"vector": [2.5, 0, 0]
						},
						"0.9167": {
							"vector": [10, 0, 0]
						},
						"1.25": {
							"vector": [2.5, 0, 0]
						}
					}
				}
			}
		},
		"Ted_Attack1": {
			"loop": true,
			"animation_length": 1,
			"bones": {
				"bone11": {
					"rotation": {
						"0.0": {
							"vector": [5, 0, 0]
						},
						"0.3333": {
							"vector": [-5.04292, 7.4713, -0.6574]
						},
						"0.4167": {
							"vector": [-5.04292, 7.4713, -0.6574]
						},
						"0.6667": {
							"vector": [4.95708, 7.4713, -0.6574]
						},
						"0.75": {
							"vector": [4.95708, 7.4713, -0.6574]
						},
						"1.0": {
							"vector": [5, 0, 0]
						}
					},
					"position": {
						"0.0": {
							"vector": [0, 0, 0]
						},
						"0.3333": {
							"vector": [0.25, 0, 0.5]
						},
						"0.4167": {
							"vector": [0.25, 0, 0.5]
						},
						"1.0": {
							"vector": [0, 0, 0]
						}
					}
				},
				"bone12": {
					"rotation": {
						"0.0": {
							"vector": [17.5, 0, 0]
						},
						"0.3333": {
							"vector": [0, 0, 0]
						},
						"0.4167": {
							"vector": [0, 0, 0]
						},
						"0.6667": {
							"vector": [10, 0, 0]
						},
						"0.75": {
							"vector": [10, 0, 0]
						},
						"1.0": {
							"vector": [17.5, 0, 0]
						}
					}
				},
				"bone13": {
					"rotation": {
						"0.0": {
							"vector": [5, 0, 0]
						},
						"0.6667": {
							"vector": [15, 0, 0]
						},
						"0.75": {
							"vector": [15, 0, 0]
						},
						"1.0": {
							"vector": [5, 0, 0]
						}
					}
				},
				"longpart_left_arm": {
					"rotation": {
						"0.0": {
							"vector": [60.03092, -90.33451, 88.75028]
						},
						"0.4167": {
							"vector": [100.11012, -84.23411, 90.11275]
						},
						"0.5": {
							"vector": [105.12596, -83.01402, 90.38524]
						},
						"0.6667": {
							"vector": [110.09428, -85.45419, 89.84025]
						},
						"0.75": {
							"vector": [102.59428, -85.45419, 89.84025]
						},
						"1.0": {
							"vector": [60.03092, -90.33451, 88.75028]
						}
					},
					"position": {
						"0.0": {
							"vector": [2, 0, 0]
						},
						"0.5": {
							"vector": [2, 0, -1]
						},
						"1.0": {
							"vector": [2, 0, 0]
						}
					}
				},
				"nails1": {
					"rotation": {
						"0.0": {
							"vector": [0, 0, 10]
						},
						"1.0": {
							"vector": [0, 0, 10]
						}
					}
				},
				"nail2": {
					"rotation": {
						"vector": [0, 0, 10]
					}
				},
				"nails3": {
					"rotation": {
						"0.0": {
							"vector": [0, 0, 10]
						},
						"1.0": {
							"vector": [0, 0, 10]
						}
					}
				},
				"longpart_right_arm": {
					"rotation": {
						"0.0": {
							"vector": [30, 0, -90]
						},
						"0.3333": {
							"vector": [-37.31965, -62.22995, 65.10133]
						},
						"0.4167": {
							"vector": [-28.86845, -64.96869, 55.67298]
						},
						"0.6667": {
							"vector": [67.50364, 36.75135, -87.55788]
						},
						"0.75": {
							"vector": [57.12212, 40.19934, -92.18559]
						},
						"1.0": {
							"vector": [30, 0, -90]
						}
					},
					"position": {
						"0.0": {
							"vector": [-2, 0, 0]
						},
						"0.3333": {
							"vector": [0, 0, 0]
						},
						"0.4167": {
							"vector": [-1, 0, 0]
						},
						"0.5": {
							"vector": [-1, 0, 0]
						},
						"0.6667": {
							"vector": [-4, 0, 0]
						},
						"0.75": {
							"vector": [-4, 0, 0]
						},
						"1.0": {
							"vector": [-2, 0, 0]
						}
					}
				},
				"nails2": {
					"rotation": {
						"0.0": {
							"vector": [0, 0, 10]
						},
						"0.4167": {
							"vector": [0, 0, 15]
						},
						"0.6667": {
							"vector": [0, 0, 32.86]
						},
						"0.75": {
							"vector": [0, 0, 27.15]
						},
						"1.0": {
							"vector": [0, 0, 10]
						}
					}
				},
				"nail3": {
					"rotation": {
						"0.0": {
							"vector": [0, 0, 10]
						},
						"0.4167": {
							"vector": [0, 0, 15]
						},
						"0.6667": {
							"vector": [0, 0, 32.86]
						},
						"1.0": {
							"vector": [0, 0, 10]
						}
					}
				},
				"nails4": {
					"rotation": {
						"0.0": {
							"vector": [0, 0, 10]
						},
						"0.4167": {
							"vector": [0, 0, 15]
						},
						"0.6667": {
							"vector": [0, 0, 32.86]
						},
						"1.0": {
							"vector": [0, 0, 10]
						}
					}
				},
				"hed": {
					"rotation": {
						"0.0": {
							"vector": [-20, 0, 0]
						},
						"0.3333": {
							"vector": [10, 0, 0]
						},
						"0.4167": {
							"vector": [5, 0, 0]
						},
						"0.6667": {
							"vector": [-0.71, 0, 0]
						},
						"0.75": {
							"vector": [4.47, 0, 0]
						},
						"1.0": {
							"vector": [-20, 0, 0]
						}
					}
				},
				"ears": {
					"rotation": {
						"0.0": {
							"vector": [0, 0, 0]
						},
						"0.3333": {
							"vector": [37.5, 0, 0]
						},
						"0.4167": {
							"vector": [30, 0, 0]
						},
						"0.6667": {
							"vector": [-11.25, 0, 0]
						},
						"0.75": {
							"vector": [-3.44, 0, 0]
						},
						"1.0": {
							"vector": [0, 0, 0]
						}
					}
				},
				"thumbnail4": {
					"rotation": {
						"0.0": {
							"vector": [0, 0, 0]
						},
						"0.6667": {
							"vector": [0, -20, 45]
						},
						"1.0": {
							"vector": [0, 0, 0]
						}
					}
				},
				"thumbnail5": {
					"rotation": {
						"0.0": {
							"vector": [0, 0, 0]
						},
						"0.6667": {
							"vector": [0, 0, 20]
						},
						"1.0": {
							"vector": [0, 0, 0]
						}
					}
				},
				"thumbnail6": {
					"rotation": {
						"0.0": {
							"vector": [0, 0, 0]
						},
						"0.6667": {
							"vector": [0, 0, 7.5]
						},
						"1.0": {
							"vector": [0, 0, 0]
						}
					}
				}
			}
		},
		"Ted_Idle": {
			"loop": true,
			"animation_length": 2.125,
			"bones": {
				"longpartrightleg": {
					"rotation": {
						"0.0": {
							"vector": [0, 0, 0]
						},
						"0.1667": {
							"vector": [0, 0, 0]
						}
					}
				},
				"longpart_right_leg_bottom": {
					"rotation": {
						"vector": [0, 0, 0]
					}
				},
				"rightfoot": {
					"rotation": {
						"vector": [0, 0, 0]
					}
				},
				"longpartlegleft": {
					"rotation": {
						"vector": [0, 0, 0]
					}
				},
				"longpart_left_leg_bottom": {
					"rotation": {
						"vector": [0.36, 0, 0]
					}
				},
				"footleft": {
					"rotation": {
						"vector": [0.71, 0, 0]
					}
				},
				"bone11": {
					"rotation": {
						"0.0": {
							"vector": [5, 0, 0]
						},
						"1.0": {
							"vector": [5, 0, 0]
						}
					}
				},
				"bone12": {
					"rotation": {
						"0.0": {
							"vector": [17.5, 0, 0]
						},
						"0.5": {
							"vector": [12.5, 0, 0]
						},
						"1.0": {
							"vector": [17.5, 0, 0]
						},
						"1.125": {
							"vector": [17.5, 0, 0]
						},
						"1.625": {
							"vector": [12.5, 0, 0]
						},
						"2.125": {
							"vector": [17.5, 0, 0]
						}
					}
				},
				"bone13": {
					"rotation": {
						"0.0": {
							"vector": [5, 0, 0]
						},
						"0.5": {
							"vector": [5, 0, 0]
						}
					}
				},
				"longpart_left_arm": {
					"rotation": {
						"vector": [60.03092, -90.33451, 88.75028]
					},
					"position": {
						"0.0": {
							"vector": [2, 0, 0]
						},
						"0.5": {
							"vector": [2, 0, -1]
						},
						"1.0": {
							"vector": [2, 0, 0]
						},
						"1.125": {
							"vector": [2, 0, 0]
						},
						"1.625": {
							"vector": [2, 0, -1]
						},
						"2.125": {
							"vector": [2, 0, 0]
						}
					}
				},
				"nails1": {
					"rotation": {
						"0.0": {
							"vector": [0, 0, 10]
						},
						"1.125": {
							"vector": [0, 0, 10]
						}
					}
				},
				"nail2": {
					"rotation": {
						"0.0": {
							"vector": [0, 0, 10]
						},
						"1.125": {
							"vector": [0, 0, 10]
						}
					}
				},
				"nails3": {
					"rotation": {
						"0.0": {
							"vector": [0, 0, 10]
						},
						"1.125": {
							"vector": [0, 0, 10]
						}
					}
				},
				"longpart_right_arm": {
					"rotation": {
						"vector": [30, 0, -90]
					},
					"position": {
						"0.0": {
							"vector": [-2, 0, 0]
						},
						"0.5": {
							"vector": [-2, 1, 0]
						},
						"1.0": {
							"vector": [-2, 0, 0]
						},
						"1.125": {
							"vector": [-2, 0, 0]
						},
						"1.625": {
							"vector": [-2, 1, 0]
						},
						"2.125": {
							"vector": [-2, 0, 0]
						}
					}
				},
				"nails2": {
					"rotation": {
						"0.0": {
							"vector": [0, 0, 10]
						},
						"1.125": {
							"vector": [0, 0, 10]
						}
					}
				},
				"nail3": {
					"rotation": {
						"0.0": {
							"vector": [0, 0, 10]
						},
						"1.125": {
							"vector": [0, 0, 10]
						}
					}
				},
				"nails4": {
					"rotation": {
						"0.0": {
							"vector": [0, 0, 10]
						},
						"1.125": {
							"vector": [0, 0, 10]
						}
					}
				},
				"hed": {
					"rotation": {
						"0.0": {
							"vector": [-20, 0, 0]
						},
						"0.5": {
							"vector": [-25, 0, 0]
						},
						"1.0": {
							"vector": [-20, 0, 0]
						},
						"1.125": {
							"vector": [-21, 0, 0]
						},
						"1.625": {
							"vector": [-25, 0, 0]
						},
						"2.125": {
							"vector": [-20, 0, 0]
						}
					}
				},
				"ears": {
					"rotation": {
						"0.0": {
							"vector": [0, 0, 0]
						},
						"0.5": {
							"vector": [15, 0, 0]
						},
						"1.0": {
							"vector": [0, 0, 0]
						},
						"1.625": {
							"vector": [15, 0, 0]
						},
						"2.125": {
							"vector": [0, 0, 0]
						}
					}
				},
				"thumbnail1": {
					"rotation": {
						"0.0": {
							"vector": [0, 0, 0]
						},
						"1.125": {
							"vector": [0, 0, 0]
						}
					}
				},
				"thumbnail2": {
					"rotation": {
						"0.0": {
							"vector": [0, 0, 0]
						},
						"1.125": {
							"vector": [0, 0, 0]
						}
					}
				},
				"thumbnail3": {
					"rotation": {
						"0.0": {
							"vector": [0, 0, 0]
						},
						"1.125": {
							"vector": [0, 0, 0]
						}
					}
				},
				"thumbnail4": {
					"rotation": {
						"0.0": {
							"vector": [0, 0, 0]
						},
						"1.125": {
							"vector": [0, 0, 0]
						}
					}
				},
				"thumbnail5": {
					"rotation": {
						"0.0": {
							"vector": [0, 0, 0]
						},
						"1.125": {
							"vector": [0, 0, 0]
						}
					}
				},
				"thumbnail6": {
					"rotation": {
						"0.0": {
							"vector": [0, 0, 0]
						},
						"1.125": {
							"vector": [0, 0, 0]
						}
					}
				}
			}
		},
		"Ted_Erect": {
			"animation_length": 7.5,
			"bones": {
				"Ted": {
					"position": {
						"0.0": {
							"vector": [0, -85, 0]
						},
						"1.0417": {
							"vector": [0, -85, 0]
						},
						"1.25": {
							"vector": [0, -79, 0]
						},
						"1.5": {
							"vector": [0, -79, 0]
						},
						"1.5833": {
							"vector": [0, -79, 0]
						},
						"2.75": {
							"vector": [0, -72, 18]
						},
						"3.5": {
							"vector": [0, -52, 18]
						},
						"3.5833": {
							"vector": [0, -52, 18]
						},
						"4.25": {
							"vector": [0, -32, 18]
						},
						"4.3333": {
							"vector": [0, -32, 18]
						},
						"5.0": {
							"vector": [0, -15, 18]
						},
						"5.5": {
							"vector": [0, -14, 18]
						},
						"6.0": {
							"vector": [0, -3, 13]
						},
						"6.5": {
							"vector": [0, -1, 11]
						},
						"7.5": {
							"vector": [0, 0, 0]
						}
					}
				},
				"longpartrightleg": {
					"rotation": {
						"0.0": {
							"vector": [0, 0, 0]
						},
						"5.0": {
							"vector": [0, 0, 0]
						},
						"6.0": {
							"vector": [17.5, 0, 0]
						},
						"6.5": {
							"vector": [20, 0, 0]
						},
						"7.5": {
							"vector": [0, 0, 0]
						}
					}
				},
				"longpartlegleft": {
					"rotation": {
						"0.0": {
							"vector": [0, 0, 0]
						},
						"5.0": {
							"vector": [0, 0, 0]
						},
						"5.5": {
							"vector": [-67.5, 0, 0]
						},
						"6.0": {
							"vector": [-40, 0, 0]
						},
						"6.5": {
							"vector": [-32.5, 0, 0]
						},
						"7.5": {
							"vector": [0, 0, 0]
						}
					}
				},
				"longpart_left_leg_bottom": {
					"rotation": {
						"0.0": {
							"vector": [0, 0, 0]
						},
						"5.0": {
							"vector": [0, 0, 0]
						},
						"5.5": {
							"vector": [25, 0, 0]
						},
						"6.0": {
							"vector": [40, 0, 0]
						},
						"6.5": {
							"vector": [32.5, 0, 0]
						},
						"7.5": {
							"vector": [0, 0, 0]
						}
					}
				},
				"bone11": {
					"rotation": {
						"0.0": {
							"vector": [0, 0, 0]
						},
						"4.0": {
							"vector": [0.5, 0, 0]
						},
						"5.0": {
							"vector": [22.5, 0, 0]
						},
						"7.5": {
							"vector": [5, 0, 0]
						}
					}
				},
				"bone12": {
					"rotation": {
						"0.0": {
							"vector": [0, 0, 0]
						},
						"2.75": {
							"vector": [7.5, 0, 0]
						},
						"3.5": {
							"vector": [12.5, 0, 0]
						},
						"3.5833": {
							"vector": [12.5, 0, 0]
						},
						"4.3333": {
							"vector": [21.47, 0, 0]
						},
						"5.0": {
							"vector": [20, 0, 0]
						},
						"6.0": {
							"vector": [20, 0, 0]
						},
						"7.5": {
							"vector": [17.5, 0, 0]
						}
					}
				},
				"bone13": {
					"rotation": {
						"0.0": {
							"vector": [0, 0, 0]
						},
						"6.5": {
							"vector": [5, 0, 0]
						},
						"7.5": {
							"vector": [5, 0, 0]
						}
					}
				},
				"longpart_left_arm": {
					"rotation": {
						"0.0": {
							"vector": [0, 0, 0]
						},
						"0.25": {
							"vector": [-90, 217.5, 90]
						},
						"0.5": {
							"vector": [-90, 277.5, 90]
						},
						"0.5833": {
							"vector": [-90, 277.5, 90]
						},
						"1.0": {
							"vector": [-90, 290, 90]
						},
						"1.0417": {
							"vector": [0, 0, 0]
						},
						"1.25": {
							"vector": [-90, -90, 90]
						},
						"1.5": {
							"vector": [-90, -90, 90]
						},
						"1.5833": {
							"vector": [-90, -90, 90]
						},
						"1.75": {
							"vector": [-64.81092, -83.20618, 93.18458]
						},
						"2.75": {
							"vector": [-49.46213, -57.40427, 45.86689]
						},
						"3.5": {
							"vector": [-70.5202, -12.90291, 2.72316]
						},
						"3.5833": {
							"vector": [-73.58932, -15.28218, -0.44046]
						},
						"3.875": {
							"vector": [21.90292, -14.17376, 92.30101]
						},
						"4.25": {
							"vector": [76.28248, -18.30155, 150.65148]
						},
						"4.3333": {
							"vector": [79.09884, -23.18821, 153.66026]
						},
						"5.0": {
							"vector": [94.58268, -42.74199, 182.94844]
						}
					},
					"position": {
						"0.0": {
							"vector": [0, 0, 0]
						},
						"0.5": {
							"vector": [0, 0, -3.5]
						},
						"0.5833": {
							"vector": [0, 0, -3.5]
						},
						"1.0": {
							"vector": [2, 0, 5]
						},
						"1.0417": {
							"vector": [0, 0, 0]
						},
						"1.25": {
							"vector": [2, 0, 21]
						},
						"1.5": {
							"vector": [2, 0, 0]
						},
						"1.5833": {
							"vector": [2, 0, 1]
						},
						"6.5": {
							"vector": [2, 0, 0]
						},
						"7.5": {
							"vector": [2, 0, 0]
						}
					}
				},
				"longpart_left_arm_bottom": {
					"rotation": {
						"0.0": {
							"vector": [0, 0, 0]
						},
						"2.75": {
							"vector": [-25, 0, 0]
						},
						"3.5833": {
							"vector": [-35.74, 0, 0]
						},
						"4.3333": {
							"vector": [-21.82, 0, 0]
						},
						"5.0": {
							"vector": [0, 0, 0]
						}
					}
				},
				"nails1": {
					"rotation": {
						"0.0": {
							"vector": [0, 0, 0]
						},
						"0.5": {
							"vector": [0, 0, 15]
						},
						"1.0": {
							"vector": [0, 0, 15]
						},
						"1.0417": {
							"vector": [0, 0, 0]
						},
						"1.5": {
							"vector": [0, 0, 17.79]
						},
						"1.5833": {
							"vector": [0, 0, 17.79]
						},
						"1.75": {
							"vector": [0, 0, 27.5]
						},
						"7.5": {
							"vector": [0, 0, 10]
						}
					}
				},
				"nail2": {
					"rotation": {
						"0.0": {
							"vector": [0, 0, 0]
						},
						"0.5": {
							"vector": [0, 0, 20]
						},
						"1.0": {
							"vector": [0, 0, 20]
						},
						"1.0417": {
							"vector": [0, 0, 0]
						},
						"1.5": {
							"vector": [0, 0, 14.56]
						},
						"1.5833": {
							"vector": [0, 0, 14.56]
						},
						"1.75": {
							"vector": [0, 0, 22.5]
						},
						"7.5": {
							"vector": [0, 0, 10]
						}
					}
				},
				"nails3": {
					"rotation": {
						"0.0": {
							"vector": [0, 0, 0]
						},
						"0.5": {
							"vector": [0, 0, 25]
						},
						"1.0": {
							"vector": [0, 0, 25]
						},
						"1.0417": {
							"vector": [0, 0, 0]
						},
						"1.5": {
							"vector": [0, 0, 16.18]
						},
						"1.5833": {
							"vector": [0, 0, 16.18]
						},
						"1.75": {
							"vector": [0, 0, 25]
						},
						"7.5": {
							"vector": [0, 0, 10]
						}
					}
				},
				"thumbnail1": {
					"rotation": {
						"0.0": {
							"vector": [0, 0, 0]
						},
						"0.5": {
							"vector": [0, 0, -10]
						},
						"1.0": {
							"vector": [0, 0, -10]
						},
						"1.5": {
							"vector": [7.88086, 35.30882, 1.20155]
						},
						"1.5833": {
							"vector": [7.88086, 35.30882, 1.20155]
						},
						"1.75": {
							"vector": [9.85108, 44.13603, 4.00194]
						},
						"7.5": {
							"vector": [0, 0, 0]
						}
					}
				},
				"thumbnail2": {
					"rotation": {
						"0.0": {
							"vector": [0, 0, 0]
						},
						"1.5": {
							"vector": [0, 0, 0]
						},
						"1.5833": {
							"vector": [0, 0, 0]
						},
						"7.5": {
							"vector": [0, 0, 0]
						}
					}
				},
				"thumbnail3": {
					"rotation": {
						"0.0": {
							"vector": [0, 0, 0]
						},
						"1.5": {
							"vector": [0, 0, 0]
						},
						"1.5833": {
							"vector": [0, 0, 0]
						},
						"7.5": {
							"vector": [0, 0, 0]
						}
					}
				},
				"longpart_right_arm": {
					"rotation": {
						"0.0": {
							"vector": [0, 0, 0]
						},
						"1.5": {
							"vector": [0, 0, 0]
						},
						"1.5833": {
							"vector": [0, 0, 0]
						},
						"2.0": {
							"vector": [-0.66298, -62.63069, 78.76438]
						},
						"2.75": {
							"vector": [90.2688, -44.58987, 6.21998]
						},
						"2.7917": {
							"vector": [90.26417, -42.78433, 6.22872]
						},
						"3.5": {
							"vector": [90.1978, -14.5901, 6.35885]
						},
						"3.5833": {
							"vector": [82.58483, -12.04899, 7.03432]
						},
						"3.875": {
							"vector": [86.01967, 4.51374, 7.36917]
						},
						"4.25": {
							"vector": [90.20117, 17.90971, 6.47055]
						},
						"4.3333": {
							"vector": [90.20782, 22.90968, 6.48958]
						},
						"5.0": {
							"vector": [91.68169, 42.92574, 5.2805]
						}
					},
					"position": {
						"0.0": {
							"vector": [0, 0, 0]
						},
						"1.5": {
							"vector": [0, 0, 0]
						},
						"1.5833": {
							"vector": [0, 0, 0]
						},
						"2.0833": {
							"vector": [-1.89, -1, 0]
						},
						"2.75": {
							"vector": [-2.5, 0, 1]
						},
						"2.7917": {
							"vector": [-2.5, 0, 2]
						},
						"6.5": {
							"vector": [-2.5, 0, 1]
						},
						"7.5": {
							"vector": [-2, 0, 0]
						}
					}
				},
				"longpart_left_arm_bottom2": {
					"rotation": {
						"0.0": {
							"vector": [0, 0, 0]
						},
						"3.5833": {
							"vector": [22.25, 0, 0]
						},
						"4.25": {
							"vector": [17.5, 0, 0]
						},
						"4.3333": {
							"vector": [17.5, 0, 0]
						},
						"5.0": {
							"vector": [2.5, 0, 0]
						}
					}
				},
				"nails2": {
					"rotation": {
						"0.0": {
							"vector": [0, 0, 0]
						},
						"2.75": {
							"vector": [0, 0, 15]
						},
						"7.5": {
							"vector": [0, 0, 10]
						}
					}
				},
				"nail3": {
					"rotation": {
						"0.0": {
							"vector": [0, 0, 0]
						},
						"2.75": {
							"vector": [0, 0, 15]
						},
						"7.5": {
							"vector": [0, 0, 10]
						}
					}
				},
				"nails4": {
					"rotation": {
						"0.0": {
							"vector": [0, 0, 0]
						},
						"2.75": {
							"vector": [0, 0, 15]
						},
						"7.5": {
							"vector": [0, 0, 10]
						}
					}
				},
				"thumbnail4": {
					"rotation": {
						"vector": [0, 0, 0]
					}
				},
				"thumbnail5": {
					"rotation": {
						"vector": [0, 0, 0]
					}
				},
				"thumbnail6": {
					"rotation": {
						"vector": [0, 0, 0]
					}
				},
				"hed": {
					"rotation": {
						"0.0": {
							"vector": [0, 0, 0]
						},
						"2.75": {
							"vector": [15, 0, 0]
						},
						"3.5": {
							"vector": [20, 0, 0]
						},
						"3.5833": {
							"vector": [20, 0, 0]
						},
						"6.0": {
							"vector": [15.5, 0, 0]
						},
						"6.5": {
							"vector": [2.5, 0, 0]
						},
						"7.5": {
							"vector": [-21, 0, 0]
						}
					}
				},
				"ears": {
					"rotation": {
						"0.0": {
							"vector": [0, 0, 0]
						},
						"1.25": {
							"vector": [52.5, 0, 0]
						},
						"3.5": {
							"vector": [52.5, 0, 0]
						},
						"4.0": {
							"vector": [30, 0, 0]
						},
						"6.5": {
							"vector": [22.5, 0, 0]
						}
					}
				}
			}
		},
		"Ted_Idle_Underground": {
			"loop": true,
			"animation_length": 1,
			"bones": {
				"Ted": {
					"rotation": {
						"0.0": {
							"vector": [0, 0, 0]
						},
						"1.0": {
							"vector": [-3240, -3240, -3240]
						}
					},
					"position": {
						"vector": [0, -89, 0]
					}
				}
			}
		}
	},
	"geckolib_format_version": 2
}